PEALS_TEST-1.2.data/scripts/peals
test/__init__.py
test/test/__init__.py
test/test/test.py
PEALS_TEST-1.2.dist-info/METADATA
PEALS_TEST-1.2.dist-info/WHEEL
PEALS_TEST-1.2.dist-info/top_level.txt
PEALS_TEST-1.2.dist-info/RECORD
