Metadata-Version: 2.1
Name: PEALS-TEST
Version: 1.2
Summary: Peak-based Enhancement Analysis Pipeline for MeRIP-Seq
Home-page: http://github.com/kerenzhou062/PEALS/
Author: Keren Zhou
Author-email: zhoukr062@gmail.com
License: UNKNOWN
Platform: UNKNOWN
Classifier: Environment :: Console
Classifier: Intended Audience :: Developers
Classifier: Intended Audience :: Science/Research
Classifier: License :: OSI Approved :: BSD License
Classifier: Operating System :: POSIX
Classifier: Operating System :: Unix
Classifier: Topic :: Scientific/Engineering :: Bio-Informatics
Classifier: Programming Language :: Python :: 3.8
Requires-Python: >=3.8
Requires-Dist: numpy (>=1.21.2)
Requires-Dist: pandas (>=1.1.4)
Requires-Dist: pysam (>=0.16.0.1)
Requires-Dist: psutil (>=5.9.4)
Requires-Dist: pyBigWig (>=0.3.18)
Requires-Dist: tqdm (>=tqdm)
Requires-Dist: rpy2 (>=3.4.5)
Requires-Dist: mpmath (>=1.1.0)
Requires-Dist: findpeaks (>=2.1.7)
Requires-Dist: csaps (>=1.1.0)
Requires-Dist: setuptools (>=45.2.0)
Requires-Dist: pytest (>=5.4.1)
